appunit/__init__.py
appunit-0.1.0.dev0.dist-info/LICENSE
appunit-0.1.0.dev0.dist-info/WHEEL
appunit-0.1.0.dev0.dist-info/METADATA
appunit-0.1.0.dev0.dist-info/RECORD
