Metadata-Version: 2.1
Name: appunit
Version: 0.1.0.dev0
Summary: 
License: MIT
Author: Anton Ruhlov
Author-email: antonruhlov@gmail.com
Requires-Python: >=3.6,<4.0
Classifier: License :: OSI Approved :: MIT License
Classifier: Programming Language :: Python :: 3
Classifier: Programming Language :: Python :: 3.6
Classifier: Programming Language :: Python :: 3.7
Classifier: Programming Language :: Python :: 3.8
Requires-Dist: starlette (>=0.13.8,<0.14.0)
